lmc_external_log_backend/__init__.py
lmc_external_log_backend/lmc_external_log_backend.py
lmc_external_log_backend-0.1.2.dist-info/METADATA
lmc_external_log_backend-0.1.2.dist-info/WHEEL
lmc_external_log_backend-0.1.2.dist-info/top_level.txt
lmc_external_log_backend-0.1.2.dist-info/RECORD
