Metadata-Version: 2.4
Name: lmc_external_log_backend
Version: 0.1.2
Summary: External logging backend implementation for LMCache
Home-page: https://github.com/opendataio/lmc_external_log_backend
Author: baoloongmao
Author-email: maobaolong@139.com
Classifier: Programming Language :: Python :: 3
Classifier: License :: OSI Approved :: Apache Software License
Classifier: Operating System :: OS Independent
Requires-Python: >=3.7
Dynamic: author
Dynamic: author-email
Dynamic: classifier
Dynamic: description
Dynamic: description-content-type
Dynamic: home-page
Dynamic: requires-python
Dynamic: summary
